logger.py
setup.cfg
setup.py
S3_Stream_Logger.egg-info/PKG-INFO
S3_Stream_Logger.egg-info/SOURCES.txt
S3_Stream_Logger.egg-info/dependency_links.txt
S3_Stream_Logger.egg-info/requires.txt
S3_Stream_Logger.egg-info/top_level.txt