Metadata-Version: 1.0
Name: S3-Stream-Logger
Version: 0.0.2
Summary: Tool for logging a never-ending stream of data to S3
Home-page: https://github.com/fbertsch/S3_Stream_Logger
Author: Frank Bertsch
Author-email: fbertsch@mozilla.com
License: UNKNOWN
Platform: UNKNOWN
